oakx_spacy/__init__.py
oakx_spacy/cli.py
oakx_spacy/spacy_implementation.py
oakx_spacy-0.1.6.dist-info/METADATA
oakx_spacy-0.1.6.dist-info/entry_points.txt
oakx_spacy-0.1.6.dist-info/WHEEL
oakx_spacy-0.1.6.dist-info/LICENSE
oakx_spacy-0.1.6.dist-info/RECORD
