Metadata-Version: 2.1
Name: oakx-spacy
Version: 0.1.6
Summary: oakx-spacy
License: BSD 3
Author: Harshad Hegde
Author-email: hhegde@lbl.gov
Requires-Python: >=3.9,<4.0
Classifier: License :: Other/Proprietary License
Classifier: Programming Language :: Python :: 3
Classifier: Programming Language :: Python :: 3.9
Classifier: Programming Language :: Python :: 3.10
Classifier: Programming Language :: Python :: 3.11
Provides-Extra: docs
Requires-Dist: click (>=8.1.3,<9.0.0)
Requires-Dist: importlib (>=1.0.4,<2.0.0)
Requires-Dist: myst-parser[docs] (>=0.18.1,<0.19.0) ; extra == "docs"
Requires-Dist: oaklib (>=0.1.69,<0.2.0)
Requires-Dist: scispacy (>=0.5.1,<0.6.0)
Requires-Dist: setuptools (>=65.0.1,<66.0.0)
Requires-Dist: spacy (>=3.4.4,<4.0.0)
Requires-Dist: sphinx-autodoc-typehints[docs] (>=1.19.4,<2.0.0) ; extra == "docs"
Requires-Dist: sphinx-click[docs] (>=4.3.0,<5.0.0) ; extra == "docs"
Requires-Dist: sphinx-rtd-theme[docs] (>=1.0.0,<2.0.0) ; extra == "docs"
Requires-Dist: sphinx[docs] (>=5.3.0,<6.0.0) ; extra == "docs"
Requires-Dist: tox (>=3.25.1,<4.0.0)
